django_switchuser/__init__.py
django_switchuser/context_processors.py
django_switchuser/middleware.py
django_switchuser/state.py
django_switchuser/urls.py
django_switchuser/views.py
django_switchuser/templates/su/login.html
django_switchuser/templates/su/login_form.html
django_switchuser/templates/su/logout.html
django_switchuser/templates/su/logout_form.html
django_switchuser/templates/su/statusbar.html
django_switchuser/templatetags/__init__.py
django_switchuser/templatetags/switchuser.py
django_switchuser-0.6.1.dist-info/DESCRIPTION.rst
django_switchuser-0.6.1.dist-info/METADATA
django_switchuser-0.6.1.dist-info/RECORD
django_switchuser-0.6.1.dist-info/WHEEL
django_switchuser-0.6.1.dist-info/metadata.json
django_switchuser-0.6.1.dist-info/pbr.json
django_switchuser-0.6.1.dist-info/top_level.txt
